fauxgeo/__init__.py
fauxgeo/affine.py
fauxgeo/raster_factory.py
fauxgeo-0.3.0.dist-info/DESCRIPTION.rst
fauxgeo-0.3.0.dist-info/METADATA
fauxgeo-0.3.0.dist-info/RECORD
fauxgeo-0.3.0.dist-info/WHEEL
fauxgeo-0.3.0.dist-info/metadata.json
fauxgeo-0.3.0.dist-info/top_level.txt
tests/__init__.py
tests/test_raster_factory.py
